{"is_source_file": false, "format": "", "description": "", "external_files": [], "external_methods": [], "published": [], "classes": [], "methods": [], "calls": [], "search-terms": ["appsettings", "json", "Logging", "LogLevel", "Development"], "state": 2, "file_id": 3, "knowledge_revision": 9, "git_revision": "0285c878ea5024d75a22a23259c619d6d2327e52", "hash": "477a525a47fc9bdbbf94690e6633d843", "format-version": 4, "code-base-name": "notes_backend", "filename": "notes_backend/appsettings.Development.json", "revision_history": [{"9": "0285c878ea5024d75a22a23259c619d6d2327e52"}]}